{"format":2,"version":"6.1.1","globals":"fac264d14ad7f51530ed5e5a35ea8ba6","files":{"d_f2af9067e8be8028_cli_py":{"hash":"6c744f9a08c6622eac01404ee3e7df26","index":{"nums":[2,1,80,0,22,18,5,11],"html_filename":"d_f2af9067e8be8028_cli_py.html","relative_filename":"src/griffe/cli.py"}},"d_f2af9067e8be8028_collections_py":{"hash":"9a9540700a3b93d18132d53a5e226aef","index":{"nums":[2,1,4,0,0,0,0,0],"html_filename":"d_f2af9067e8be8028_collections_py.html","relative_filename":"src/griffe/collections.py"}},"d_f2af9067e8be8028_dataclasses_py":{"hash":"8b0ebeb76982ca1fa3eb6c799de7e25c","index":{"nums":[2,1,229,0,33,62,12,24],"html_filename":"d_f2af9067e8be8028_dataclasses_py.html","relative_filename":"src/griffe/dataclasses.py"}},"d_0468c13ba1fa8830_dataclasses_py":{"hash":"67170b3e92aee1055cc0c0ed708c7cdd","index":{"nums":[2,1,65,0,15,6,0,6],"html_filename":"d_0468c13ba1fa8830_dataclasses_py.html","relative_filename":"src/griffe/docstrings/dataclasses.py"}},"d_0468c13ba1fa8830_google_py":{"hash":"51d4ced31130a8ff269888bb48f69c6b","index":{"nums":[2,1,291,0,65,116,12,26],"html_filename":"d_0468c13ba1fa8830_google_py.html","relative_filename":"src/griffe/docstrings/google.py"}},"d_0468c13ba1fa8830_markdown_py":{"hash":"c1e17164754910eb08783e5c678744ab","index":{"nums":[2,1,0,0,0,0,0,0],"html_filename":"d_0468c13ba1fa8830_markdown_py.html","relative_filename":"src/griffe/docstrings/markdown.py"}},"d_0468c13ba1fa8830_numpy_py":{"hash":"06233e1377a692c4455c04f44e4afc29","index":{"nums":[2,1,275,0,46,124,29,33],"html_filename":"d_0468c13ba1fa8830_numpy_py.html","relative_filename":"src/griffe/docstrings/numpy.py"}},"d_0468c13ba1fa8830_parsers_py":{"hash":"c5a96b001a8046f57989cbf6c75fb77f","index":{"nums":[2,1,18,0,4,4,1,3],"html_filename":"d_0468c13ba1fa8830_parsers_py.html","relative_filename":"src/griffe/docstrings/parsers.py"}},"d_0468c13ba1fa8830_rst_py":{"hash":"5eb726c37e60084d2da2e0c5bc338e84","index":{"nums":[2,1,217,0,4,86,2,4],"html_filename":"d_0468c13ba1fa8830_rst_py.html","relative_filename":"src/griffe/docstrings/rst.py"}},"d_0468c13ba1fa8830_utils_py":{"hash":"6d382dfb5b53e67da8d3ea9e35458559","index":{"nums":[2,1,14,0,6,2,1,1],"html_filename":"d_0468c13ba1fa8830_utils_py.html","relative_filename":"src/griffe/docstrings/utils.py"}},"d_f2af9067e8be8028_encoders_py":{"hash":"dc7e34c0437593b87eab3aa8ea9e0f8a","index":{"nums":[2,1,41,0,19,22,2,16],"html_filename":"d_f2af9067e8be8028_encoders_py.html","relative_filename":"src/griffe/encoders.py"}},"d_f2af9067e8be8028_extended_ast_py":{"hash":"1274b4ad3ee7ab51dd779d91a8510154","index":{"nums":[2,1,77,0,21,22,2,4],"html_filename":"d_f2af9067e8be8028_extended_ast_py.html","relative_filename":"src/griffe/extended_ast.py"}},"d_eb98acfce92038d0_base_py":{"hash":"439ea352ea0ca9cb8bc7d4b27c90d3a0","index":{"nums":[2,1,61,0,9,16,2,2],"html_filename":"d_eb98acfce92038d0_base_py.html","relative_filename":"src/griffe/extensions/base.py"}},"d_f2af9067e8be8028_loader_py":{"hash":"793b3fe80f240228984162c23a217af7","index":{"nums":[2,1,137,0,47,48,7,23],"html_filename":"d_f2af9067e8be8028_loader_py.html","relative_filename":"src/griffe/loader.py"}},"d_f2af9067e8be8028_logger_py":{"hash":"5280cb2f69c3799db3902560e26c87ff","index":{"nums":[2,1,3,0,0,0,0,0],"html_filename":"d_f2af9067e8be8028_logger_py.html","relative_filename":"src/griffe/logger.py"}},"d_f2af9067e8be8028_visitor_py":{"hash":"3369acb233a10fafb169f06e82574275","index":{"nums":[2,1,343,0,55,142,14,52],"html_filename":"d_f2af9067e8be8028_visitor_py.html","relative_filename":"src/griffe/visitor.py"}},"d_a44f0ac069e85531_conftest_py":{"hash":"65478c9a360455166c1c8c4e2b1d8444","index":{"nums":[2,1,0,0,0,0,0,0],"html_filename":"d_a44f0ac069e85531_conftest_py.html","relative_filename":"tests/conftest.py"}},"d_a44f0ac069e85531_test_cli_py":{"hash":"5ced701abbbf2190cd16f0d81c38f3f5","index":{"nums":[2,1,9,0,0,2,0,0],"html_filename":"d_a44f0ac069e85531_test_cli_py.html","relative_filename":"tests/test_cli.py"}},"d_eb24e90c7b74ae12___init___py":{"hash":"334b527fca0f6ae2d623a17052a518da","index":{"nums":[2,1,0,0,0,0,0,0],"html_filename":"d_eb24e90c7b74ae12___init___py.html","relative_filename":"tests/test_docstrings/__init__.py"}},"d_eb24e90c7b74ae12_helpers_py":{"hash":"4e50341038a65eeba56fddb3c40e8a81","index":{"nums":[2,1,28,0,0,4,0,0],"html_filename":"d_eb24e90c7b74ae12_helpers_py.html","relative_filename":"tests/test_docstrings/helpers.py"}},"d_eb24e90c7b74ae12_test_google_py":{"hash":"b564f9215fe7482b890587673df765e0","index":{"nums":[2,1,213,0,0,14,0,0],"html_filename":"d_eb24e90c7b74ae12_test_google_py.html","relative_filename":"tests/test_docstrings/test_google.py"}},"d_eb24e90c7b74ae12_test_numpy_py":{"hash":"ac394ff4d242ff300540baf2fe90214f","index":{"nums":[2,1,91,0,0,0,0,0],"html_filename":"d_eb24e90c7b74ae12_test_numpy_py.html","relative_filename":"tests/test_docstrings/test_numpy.py"}},"d_eb24e90c7b74ae12_test_rst_py":{"hash":"9c68366348faa3bf029fb34516533466","index":{"nums":[2,1,252,0,0,0,0,0],"html_filename":"d_eb24e90c7b74ae12_test_rst_py.html","relative_filename":"tests/test_docstrings/test_rst.py"}},"d_a44f0ac069e85531_test_functions_py":{"hash":"c4181de49b85a02ad385145b65385f67","index":{"nums":[2,1,145,0,0,0,0,0],"html_filename":"d_a44f0ac069e85531_test_functions_py.html","relative_filename":"tests/test_functions.py"}}}}